<?xml version="1.0" encoding="utf-8"?>
<assets PGFVersion="0.19" GSCVersion="0.10.5">
  <sounds />
  <images>
    <image name="leg platform">
      <file name="leg platform.png" size="3360" />
    </image>
    <image name="pant platform">
      <file name="pant platform.png" size="5503" />
    </image>
    <image name="hand platform">
      <file name="hand platform.png" size="6762" />
    </image>
    <image name="hand">
      <file name="hand.png" size="3274" />
    </image>
    <image name="leg">
      <file name="leg.png" size="1702" />
    </image>
    <image name="pant">
      <file name="pant.png" size="1913" />
    </image>
  </images>
  <behaviors />
</assets>